dovekie/__init__.py
dovekie/core.py
dovekie-0.7.0.dist-info/LICENSE
dovekie-0.7.0.dist-info/METADATA
dovekie-0.7.0.dist-info/WHEEL
dovekie-0.7.0.dist-info/top_level.txt
dovekie-0.7.0.dist-info/RECORD
