Metadata-Version: 2.1
Name: dovekie
Version: 0.7.0
Summary: A library that defines common SKI combinators from Combinatory Logic.
Home-page: UNKNOWN
Author: Conor Hoekstra
Author-email: codereport@outlook.com
License: MIT
Platform: UNKNOWN
Requires-Python: >=3.6
License-File: LICENSE
